oxlate/__init__.py
oxlate/event.py
oxlate/headers.py
oxlate/request.py
oxlate/response.py
tests/__init__.py
tests/pytest_regex.py
tests/test_event.py
tests/test_headers.py
tests/test_request.py
tests/test_response.py
oxlate-0.0.1.dist-info/LICENSE.txt
oxlate-0.0.1.dist-info/METADATA
oxlate-0.0.1.dist-info/WHEEL
oxlate-0.0.1.dist-info/top_level.txt
oxlate-0.0.1.dist-info/RECORD
