Metadata-Version: 2.1
Name: oxlate
Version: 0.0.1
Summary: OpenStax Lambda@Edge utilities
Home-page: https://github.com/openstax/late-python
Author: JP Slavinsky
Author-email: jps@rice.edu
License: UNKNOWN
Platform: UNKNOWN
Classifier: Programming Language :: Python :: 3
Classifier: License :: OSI Approved :: MIT License
Classifier: Operating System :: OS Independent
Requires-Python: >=3.6
